MANIFEST.in
README.txt
bootstrap.py
buildout.cfg
nose.cfg
setup.py
src/geo/__init__.py
src/geo/geocell.py
src/geo/geomath.py
src/geo/geomodel.py
src/geo/geotypes.py
src/geo/util.py
src/geo/tests/app.yaml
src/geo/tests/geomodel.txt
src/geomodel.egg-info/PKG-INFO
src/geomodel.egg-info/SOURCES.txt
src/geomodel.egg-info/dependency_links.txt
src/geomodel.egg-info/not-zip-safe
src/geomodel.egg-info/requires.txt
src/geomodel.egg-info/top_level.txt