Metadata-Version: 1.0
Name: geomodel
Version: 0.1.0
Summary: Indexing and querying geospatial data in App Engine.
Home-page: http://code.google.com/p/geomodel/
Author: Roman Nurik
Author-email: api dot roman dot public at gmail dot com (Roman Nurik)
License: Apache License 2.0
Keywords: appengine gae geomodel google maps
Platform: UNKNOWN
Classifier: Development Status :: 5 - Production/Stable
Classifier: Environment :: Web Environment
Classifier: Intended Audience :: Developers
Classifier: License :: OSI Approved :: Apache Software License
Classifier: Programming Language :: Python
Classifier: Topic :: Internet :: WWW/HTTP
